htmlPy/__init__.py
htmlPy/app_gui.py
htmlPy/base_gui.py
htmlPy/binder.js
htmlPy/descriptors.py
htmlPy/gui_helper.py
htmlPy/settings.py
htmlPy/web_app_gui.py
htmlPy-2.0.3.dist-info/DESCRIPTION.rst
htmlPy-2.0.3.dist-info/METADATA
htmlPy-2.0.3.dist-info/RECORD
htmlPy-2.0.3.dist-info/WHEEL
htmlPy-2.0.3.dist-info/metadata.json
htmlPy-2.0.3.dist-info/pbr.json
htmlPy-2.0.3.dist-info/top_level.txt
