Metadata-Version: 2.0
Name: htmlPy
Version: 2.0.3
Summary: A wrapper around PySide's QtWebKit library which helps developer create beautiful UI with HTML5, CSS and Javascript for standalone applications.
Home-page: http://pypi.python.org/pypi/htmlPy/
Author: Amol Mandhane
Author-email: amol.mandhane@gmail.com
License: LICENSE.txt
Platform: UNKNOWN
Classifier: Development Status :: 5 - Production/Stable
Classifier: Intended Audience :: Developers
Classifier: License :: OSI Approved :: MIT License
Classifier: Operating System :: OS Independent
Classifier: Programming Language :: Python
Classifier: Programming Language :: Python :: 2
Classifier: Programming Language :: Python :: 2.7
Classifier: Programming Language :: Python :: 3
Classifier: Programming Language :: Python :: 3.2
Classifier: Programming Language :: Python :: 3.3
Classifier: Programming Language :: Python :: 3.4
Classifier: Topic :: Software Development :: User Interfaces
Requires: Jinja2(>=2.6)
